dottorrent_cli-1.10.3.dist-info/DESCRIPTION.rst
dottorrent_cli-1.10.3.dist-info/METADATA
dottorrent_cli-1.10.3.dist-info/RECORD
dottorrent_cli-1.10.3.dist-info/WHEEL
dottorrent_cli-1.10.3.dist-info/entry_points.txt
dottorrent_cli-1.10.3.dist-info/metadata.json
dottorrent_cli-1.10.3.dist-info/top_level.txt
dtcli/__init__.py
dtcli/cli.py
dtcli/version.py
