Metadata-Version: 1.1
Name: dottorrent-cli
Version: 1.10.3
Summary: CLI tool for creating .torrent files
Home-page: https://github.com/kz26/dottorrent-cli
Author: Kevin Zhang
Author-email: kevin@kevinzhang.me
License: UNKNOWN
Keywords: bittorrent torrent bencode cli
Platform: UNKNOWN
Classifier: Development Status :: 5 - Production/Stable
Classifier: Intended Audience :: End Users/Desktop
Classifier: License :: OSI Approved :: MIT License
Classifier: Programming Language :: Python :: 3.3
Classifier: Programming Language :: Python :: 3.4
Classifier: Programming Language :: Python :: 3.5
Classifier: Programming Language :: Python :: 3.6
